environsettings/__init__.py
environsettings/py.typed
environsettings-0.0.1.dist-info/METADATA
environsettings-0.0.1.dist-info/WHEEL
environsettings-0.0.1.dist-info/entry_points.txt
environsettings-0.0.1.dist-info/licenses/LICENSE
environsettings-0.0.1.dist-info/RECORD
