Metadata-Version: 2.4
Name: environsettings
Version: 0.0.1
Summary: Typed, validated settings management from environment variables and .env files.
Project-URL: Homepage, https://github.com/shaileshpandit141/environsettings
Project-URL: Repository, https://github.com/shaileshpandit141/environsettings
Project-URL: Issues, https://github.com/shaileshpandit141/environsettings/issues
Author-email: shaileshpandit141 <shaileshpandit141@gmail.com>
License: # MIT License
License-File: LICENSE
Keywords: configuration,dotenv,environment,settings
Classifier: Development Status :: 1 - Planning
Classifier: Intended Audience :: Developers
Classifier: License :: OSI Approved :: MIT License
Classifier: Operating System :: OS Independent
Classifier: Programming Language :: Python
Classifier: Programming Language :: Python :: 3.8
Classifier: Programming Language :: Python :: 3.9
Classifier: Programming Language :: Python :: 3.10
Classifier: Programming Language :: Python :: 3.11
Classifier: Programming Language :: Python :: 3.12
Classifier: Programming Language :: Python :: 3.13
Classifier: Topic :: Software Development :: Libraries
Classifier: Topic :: Software Development :: Libraries :: Python Modules
Requires-Python: >=3.13
Requires-Dist: python-dotenv>=1.1.1
Provides-Extra: dev
Requires-Dist: mypy; extra == 'dev'
Requires-Dist: pytest; extra == 'dev'
Requires-Dist: ruff; extra == 'dev'
